huaweicloudsdkidme/__init__.py
huaweicloudsdkidme/v1/__init__.py
huaweicloudsdkidme/v1/idme_async_client.py
huaweicloudsdkidme/v1/idme_client.py
huaweicloudsdkidme/v1/model/__init__.py
huaweicloudsdkidme/v1/model/app_user_list.py
huaweicloudsdkidme/v1/model/create_xdm_application_request.py
huaweicloudsdkidme/v1/model/create_xdm_application_request_body.py
huaweicloudsdkidme/v1/model/create_xdm_application_response.py
huaweicloudsdkidme/v1/model/delete_cloud_service_request.py
huaweicloudsdkidme/v1/model/delete_cloud_service_response.py
huaweicloudsdkidme/v1/model/delete_xdm_application_request.py
huaweicloudsdkidme/v1/model/delete_xdm_application_response.py
huaweicloudsdkidme/v1/model/deploy_application_request.py
huaweicloudsdkidme/v1/model/deploy_application_request_body.py
huaweicloudsdkidme/v1/model/deploy_application_response.py
huaweicloudsdkidme/v1/model/list_apps_request.py
huaweicloudsdkidme/v1/model/list_apps_response.py
huaweicloudsdkidme/v1/model/list_apps_response_body_result.py
huaweicloudsdkidme/v1/model/list_envs_request.py
huaweicloudsdkidme/v1/model/list_envs_response.py
huaweicloudsdkidme/v1/model/list_envs_response_body_result.py
huaweicloudsdkidme/v1/model/modify_application_request.py
huaweicloudsdkidme/v1/model/modify_application_request_body.py
huaweicloudsdkidme/v1/model/modify_application_response.py
huaweicloudsdkidme/v1/model/subscribe_cloud_service_request.py
huaweicloudsdkidme/v1/model/subscribe_cloud_service_response.py
huaweicloudsdkidme/v1/model/uninstall_request.py
huaweicloudsdkidme/v1/model/uninstall_response.py
huaweicloudsdkidme/v1/region/__init__.py
huaweicloudsdkidme/v1/region/idme_region.py
huaweicloudsdkidme-3.1.184.dist-info/METADATA
huaweicloudsdkidme-3.1.184.dist-info/WHEEL
huaweicloudsdkidme-3.1.184.dist-info/licenses/LICENSE
huaweicloudsdkidme-3.1.184.dist-info/RECORD
